keystore/__init__.py
keystore/config_reader.py
keystore/load.py
keystore/save.py
keystore-0.3.0.data/scripts/keystore-load
keystore-0.3.0.data/scripts/keystore-save
keystore-0.3.0.dist-info/DESCRIPTION.rst
keystore-0.3.0.dist-info/METADATA
keystore-0.3.0.dist-info/RECORD
keystore-0.3.0.dist-info/WHEEL
keystore-0.3.0.dist-info/metadata.json
keystore-0.3.0.dist-info/top_level.txt
