Metadata-Version: 2.0
Name: keystore
Version: 0.3.0
Summary: Command line tools to compress and encrypt your keys
Home-page: https://github.com/Spaxe/keystore
Author: Xavier Ho
Author-email: contact@xavierho.com
License: UNKNOWN
Download-URL: https://github.com/Spaxe/keystore/archive/master.zip
Keywords: keys,tokens,archive
Platform: UNKNOWN
Classifier: Programming Language :: Python
Classifier: Programming Language :: Python :: 3
Classifier: Development Status :: 2 - Pre-Alpha
Classifier: Environment :: Console
Classifier: Intended Audience :: Developers
Classifier: License :: OSI Approved :: MIT License
Classifier: Operating System :: MacOS
Classifier: Operating System :: POSIX
Classifier: Operating System :: Unix
Classifier: Topic :: System :: Archiving :: Backup
Classifier: Topic :: System :: Archiving :: Compression
Classifier: Topic :: Security
Classifier: Topic :: Security :: Cryptography
Requires-Dist: rncryptor (==3.2.0)
Requires-Dist: docopt (==0.6.2)
